ctlearn/__init__.py
ctlearn/_version.py
ctlearn/conftest.py
ctlearn/utils.py
ctlearn/core/attention.py
ctlearn/core/loader.py
ctlearn/core/model.py
ctlearn/core/tests/test_loader.py
ctlearn/tools/__init__.py
ctlearn/tools/predict_LST1.py
ctlearn/tools/predict_model.py
ctlearn/tools/train_model.py
ctlearn-0.10.2.dist-info/licenses/LICENSE
ctlearn-0.10.2.dist-info/METADATA
ctlearn-0.10.2.dist-info/WHEEL
ctlearn-0.10.2.dist-info/entry_points.txt
ctlearn-0.10.2.dist-info/top_level.txt
ctlearn-0.10.2.dist-info/RECORD
