Metadata-Version: 2.4
Name: CTLearn
Version: 0.10.2
Summary: CTLearn is a package under active development to run deep learning models to analyze data from all major current and future arrays of imaging atmospheric Cherenkov telescopes (IACTs).
Author: Ari Brill, Bryan Kim, Tjark Miener
Author-email: Daniel Nieto <d.nieto@ucm.es>
License: BSD-3-Clause
Project-URL: repository, https://github.com/ctlearn-project/ctlearn
Project-URL: documentation, https://ctlearn.readthedocs.io/en/latest/
Classifier: License :: OSI Approved :: BSD License
Classifier: Intended Audience :: Science/Research
Classifier: Topic :: Scientific/Engineering :: Astronomy
Classifier: Topic :: Scientific/Engineering :: Physics
Classifier: Programming Language :: Python :: 3
Classifier: Programming Language :: Python :: 3.10
Classifier: Programming Language :: Python :: 3.11
Classifier: Programming Language :: Python :: 3.12
Requires-Python: >=3.10
License-File: LICENSE
Requires-Dist: dl1_data_handler<0.15,>=0.14.1
Requires-Dist: astropy
Requires-Dist: numpy
Requires-Dist: pandas
Requires-Dist: pip
Requires-Dist: pyyaml
Requires-Dist: scikit-learn
Requires-Dist: numba
Requires-Dist: tensorflow<2.15,>=2.14
Requires-Dist: pydot
Requires-Dist: setuptools
Requires-Dist: ctapipe<0.24,>=0.22.0
Provides-Extra: doc
Requires-Dist: sphinx; extra == "doc"
Requires-Dist: sphinx-rtd-theme; extra == "doc"
Provides-Extra: all
Requires-Dist: ctlearn[doc]; extra == "all"
Dynamic: license-file
